Metadata-Version: 2.3
Name: drf-redesign
Version: 0.6.0
Summary: Redesign of the browse-able api of Django REST Framework with Bootstrap 5
License: MIT
Author: Yousef Abu Shanab
Author-email: josephyousef249@gmail.com
Requires-Python: >=3.10
Classifier: License :: OSI Approved :: MIT License
Classifier: Programming Language :: Python :: 3
Classifier: Programming Language :: Python :: 3.10
Classifier: Programming Language :: Python :: 3.11
Classifier: Programming Language :: Python :: 3.12
Classifier: Programming Language :: Python :: 3.13
Requires-Dist: django (>=4.0)
Requires-Dist: djangorestframework (>=3.14)
Project-URL: Homepage, https://github.com/youzarsiph/drf-redesign/
Project-URL: Repository, https://github.com/youzarsiph/drf-redesign/
